lemniscat/plugin/terraform/__init__.py
lemniscat/plugin/terraform/azurecli.py
lemniscat/plugin/terraform/main.py
lemniscat/plugin/terraform/plugin.yaml
lemniscat/plugin/terraform/requirements.txt
lemniscat/plugin/terraform/terraform.py
lemniscat/plugin/terraform/tfstate.py
lemniscat.plugin.terraform-0.4.2.dist-info/LICENSE
lemniscat.plugin.terraform-0.4.2.dist-info/METADATA
lemniscat.plugin.terraform-0.4.2.dist-info/WHEEL
lemniscat.plugin.terraform-0.4.2.dist-info/top_level.txt
lemniscat.plugin.terraform-0.4.2.dist-info/RECORD
