Metadata-Version: 2.1
Name: lemniscat.plugin.terraform
Version: 0.4.2
Summary: A runtime to provide product oriented in DevOps approach
Author-email: Philippe MORISSEAU <philippe.morisseau@outlook.com>
License: MIT
Project-URL: Homepage, https://github.com/lemniscat-devops/lemniscat.plugin.terraform
Project-URL: Issues, https://github.com/lemniscat-devops/lemniscat.plugin.terraform/issues
Classifier: Programming Language :: Python :: 3
Classifier: License :: OSI Approved :: MIT License
Classifier: Operating System :: OS Independent
Requires-Python: >=3.10
License-File: LICENSE
Requires-Dist: lemniscat.core>=0.2.1
Requires-Dist: PyYAML==6.0.1
Requires-Dist: pytz==2023.3
